LICENCE
README.md
logo.png
pyproject.toml
requirements.txt
skreducedmodel.pdf
scikit_reducedmodel.egg-info/PKG-INFO
scikit_reducedmodel.egg-info/SOURCES.txt
scikit_reducedmodel.egg-info/dependency_links.txt
scikit_reducedmodel.egg-info/requires.txt
scikit_reducedmodel.egg-info/top_level.txt
skreducedmodel/__init__.py
skreducedmodel/empiricalinterpolation.py
skreducedmodel/integrals.py
skreducedmodel/mksurrogate.py
skreducedmodel/reducedbasis.py
skreducedmodel/reducedorderquadrature.py
skreducedmodel/surrogate.py