Metadata-Version: 2.4
Name: scikit-reducedmodel
Version: 1.2
Summary: Construction of Reduced Models in Python
Author-email: Franco Cerino <francocerino@gmail.com>
License: The MIT License
Project-URL: Homepage, https://github.com/francocerino/scikit-reducedmodel
Keywords: reduced order model,machine learning,gravitational waves,reduced basis,surrogate model
Classifier: Development Status :: 4 - Beta
Classifier: Intended Audience :: Education
Classifier: Intended Audience :: Science/Research
Classifier: License :: OSI Approved :: MIT License
Classifier: Operating System :: OS Independent
Classifier: Programming Language :: Python
Classifier: Programming Language :: Python :: 3.10
Classifier: Programming Language :: Python :: Implementation :: CPython
Classifier: Topic :: Scientific/Engineering
License-File: LICENCE
Requires-Dist: numpy
Requires-Dist: scipy
Requires-Dist: anytree
Requires-Dist: attr
Requires-Dist: attrs
Requires-Dist: gwtools
Requires-Dist: scikit-learn
Dynamic: license-file
